topsis/__init__.py
topsis/topsis.py
topsis_daksh_102303322-1.0.3.dist-info/licenses/LICENSE
topsis_daksh_102303322-1.0.3.dist-info/METADATA
topsis_daksh_102303322-1.0.3.dist-info/WHEEL
topsis_daksh_102303322-1.0.3.dist-info/entry_points.txt
topsis_daksh_102303322-1.0.3.dist-info/top_level.txt
topsis_daksh_102303322-1.0.3.dist-info/RECORD
