Metadata-Version: 2.4
Name: topsis-daksh-102303322
Version: 1.0.3
Summary: Educational TOPSIS implementation in Python
Author: Daksh Garg
License: MIT
Requires-Python: >=3.8
License-File: LICENSE
Requires-Dist: numpy
Requires-Dist: pandas
Dynamic: license-file
